housing_prediction/VERSION
housing_prediction/__init__.py
housing_prediction/config.yml
housing_prediction/pipeline.py
housing_prediction/predict.py
housing_prediction/train_pipeline.py
housing_prediction/config/core.py
housing_prediction/datasets/__init__.py
housing_prediction/processing/__init__.py
housing_prediction/processing/data_manager.py
housing_prediction/processing/features.py
housing_prediction/processing/validation.py
housing_prediction/trained_models/housing_predicion_model_output1.0.0.pkl
housing_prediction_model-1.0.0.dist-info/METADATA
housing_prediction_model-1.0.0.dist-info/WHEEL
housing_prediction_model-1.0.0.dist-info/top_level.txt
housing_prediction_model-1.0.0.dist-info/RECORD
